ersatz/__init__.py
ersatz/candidates.py
ersatz/dataset.py
ersatz/determiner.py
ersatz/model.py
ersatz/score.py
ersatz/split.py
ersatz/subword.py
ersatz/trainer.py
ersatz/utils.py
ersatz-1.0.0.dist-info/LICENSE
ersatz-1.0.0.dist-info/METADATA
ersatz-1.0.0.dist-info/WHEEL
ersatz-1.0.0.dist-info/entry_points.txt
ersatz-1.0.0.dist-info/top_level.txt
ersatz-1.0.0.dist-info/RECORD
